{
  "schemaVersion": 1,
  "id": "shown",
  "version": "${version}",
  "name": "Shown",
  "description": "A widget-based UI system for Minecraft mods!",
  "authors": [
    "GDPulsar"
  ],
  "contact": {
    "homepage": ""
  },
  "license": "All-Rights-Reserved",
  "icon": "assets/shown/icon.png",
  "environment": "*",
  "entrypoints": {
    "main": [
      "com.pulsar.shown.fabric.ShownFabric"
    ],
    "client": [
      "com.pulsar.shown.fabric.client.ShownFabricClient"
    ]
  },
  "mixins": [
    "shown.mixins.json"
  ],
  "depends": {
    "fabricloader": ">=0.18.3",
    "minecraft": "~1.21.1",
    "java": ">=21",
    "architectury": ">=13.0.8",
    "fabric-api": "*"
  },
  "suggests": {
    "another-mod": "*"
  }
}
